{
  "id" : "newForm3",
  "name" : "newForm3",
  "type" : "form",
  "uuid" : "420b987b-c1bf-4b7d-91c6-13f452094a66",
  "modelVersion" : "2.6",
  "previousArtifactVersion" : "2.4",
  "lastUpdate" : 1722535000004,
  "description" : "Page generated with Bonita UI designer",
  "rows" : [
    [
      {
        "type" : "container",
        "dimension" : {
          "xs" : 12
        },
        "propertyValues" : { },
        "reference" : "fb3b0be0-d7bc-4fbd-aa83-2653c13f3bce",
        "hasValidationError" : false,
        "id" : "pbContainer",
        "rows" : [
          [
            {
              "type" : "component",
              "dimension" : {
                "md" : 12,
                "sm" : 12,
                "xs" : 12,
                "lg" : 12
              },
              "propertyValues" : {
                "hidden" : {
                  "type" : "constant",
                  "value" : false
                },
                "level" : {
                  "type" : "constant",
                  "value" : "Level 1"
                },
                "cssClasses" : {
                  "type" : "constant",
                  "value" : ""
                },
                "text" : {
                  "type" : "interpolation",
                  "value" : "{{ task.displayName }}"
                },
                "alignment" : {
                  "type" : "constant",
                  "value" : "center"
                },
                "dimension" : {
                  "type" : "constant",
                  "value" : 12
                }
              },
              "reference" : "981fa0f4-ec5c-412d-8d6b-2a7c7ae27015",
              "hasValidationError" : false,
              "id" : "pbTitle",
              "description" : ""
            }
          ],
          [
            {
              "type" : "component",
              "dimension" : {
                "md" : 12,
                "sm" : 12,
                "xs" : 12,
                "lg" : 12
              },
              "propertyValues" : {
                "allowHtml" : {
                  "type" : "constant",
                  "value" : true
                },
                "labelHidden" : {
                  "type" : "constant",
                  "value" : true
                },
                "hidden" : {
                  "type" : "constant",
                  "value" : false
                },
                "cssClasses" : {
                  "type" : "constant",
                  "value" : ""
                },
                "label" : {
                  "type" : "interpolation"
                },
                "text" : {
                  "type" : "interpolation",
                  "value" : "{{ task.displayDescription }}"
                },
                "alignment" : {
                  "type" : "constant",
                  "value" : "left"
                },
                "dimension" : {
                  "type" : "constant",
                  "value" : 12
                }
              },
              "reference" : "2056db82-35a0-44a5-8b0d-642f712b1119",
              "hasValidationError" : false,
              "id" : "pbText",
              "description" : ""
            }
          ]
        ]
      }
    ],
    [
      {
        "type" : "formContainer",
        "dimension" : {
          "xs" : 12
        },
        "propertyValues" : { },
        "reference" : "10ea8949-2b6c-4e4e-b38a-1454369a6609",
        "hasValidationError" : false,
        "id" : "pbFormContainer",
        "container" : {
          "type" : "container",
          "dimension" : {
            "xs" : 12
          },
          "propertyValues" : { },
          "reference" : "a61eaca3-2d77-4309-9ceb-27db964f8f99",
          "hasValidationError" : false,
          "id" : "pbContainer",
          "rows" : [
            [
              {
                "type" : "component",
                "dimension" : {
                  "md" : 12,
                  "sm" : 12,
                  "xs" : 12,
                  "lg" : 12
                },
                "propertyValues" : {
                  "hidden" : {
                    "type" : "constant",
                    "value" : false
                  },
                  "level" : {
                    "type" : "constant",
                    "value" : "Level 4"
                  },
                  "cssClasses" : {
                    "type" : "constant",
                    "value" : ""
                  },
                  "text" : {
                    "type" : "interpolation",
                    "value" : "Llene las Observaciones Correspondientes"
                  },
                  "alignment" : {
                    "type" : "constant",
                    "value" : "left"
                  },
                  "dimension" : {
                    "type" : "constant",
                    "value" : 12
                  },
                  "allowHTML" : {
                    "type" : "constant",
                    "value" : false
                  }
                },
                "reference" : "80a292ea-39ab-405a-a14b-59e404445377",
                "hasValidationError" : false,
                "id" : "pbTitle",
                "description" : ""
              }
            ],
            [
              {
                "type" : "container",
                "dimension" : {
                  "md" : 12,
                  "sm" : 12,
                  "xs" : 12,
                  "lg" : 12
                },
                "propertyValues" : {
                  "repeatedCollection" : {
                    "type" : "variable"
                  },
                  "hidden" : {
                    "type" : "constant",
                    "value" : false
                  },
                  "cssClasses" : {
                    "type" : "constant",
                    "value" : ""
                  },
                  "dimension" : {
                    "type" : "constant",
                    "value" : 12
                  }
                },
                "reference" : "857d8c64-78fc-4c27-9f87-11f5f5ee0f24",
                "hasValidationError" : false,
                "id" : "pbContainer",
                "rows" : [
                  [
                    {
                      "type" : "component",
                      "dimension" : {
                        "md" : 12,
                        "sm" : 12,
                        "xs" : 12,
                        "lg" : 12
                      },
                      "propertyValues" : {
                        "labelHidden" : {
                          "type" : "constant",
                          "value" : false
                        },
                        "hidden" : {
                          "type" : "constant",
                          "value" : false
                        },
                        "labelPosition" : {
                          "type" : "constant",
                          "value" : "top"
                        },
                        "cssClasses" : {
                          "type" : "constant",
                          "value" : ""
                        },
                        "labelWidth" : {
                          "type" : "constant",
                          "value" : 1
                        },
                        "readOnly" : {
                          "type" : "constant",
                          "value" : false
                        },
                        "label" : {
                          "type" : "interpolation",
                          "value" : "Observaciones_revision"
                        },
                        "placeholder" : {
                          "type" : "constant"
                        },
                        "type" : {
                          "type" : "constant",
                          "value" : "text"
                        },
                        "dimension" : {
                          "type" : "constant",
                          "value" : 12
                        },
                        "value" : {
                          "type" : "variable",
                          "value" : "variableInv.observaciones_revision"
                        },
                        "required" : {
                          "type" : "constant",
                          "value" : false
                        }
                      },
                      "reference" : "4aac8399-b992-4ed2-9682-874f0fefeec5",
                      "hasValidationError" : false,
                      "id" : "pbInput",
                      "description" : ""
                    }
                  ]
                ]
              }
            ],
            [
              {
                "type" : "component",
                "dimension" : {
                  "md" : 12,
                  "sm" : 12,
                  "xs" : 12,
                  "lg" : 12
                },
                "propertyValues" : {
                  "removeItem" : {
                    "type" : "variable"
                  },
                  "hidden" : {
                    "type" : "constant",
                    "value" : false
                  },
                  "cssClasses" : {
                    "type" : "constant",
                    "value" : ""
                  },
                  "buttonStyle" : {
                    "type" : "constant",
                    "value" : "primary"
                  },
                  "label" : {
                    "type" : "interpolation",
                    "value" : "Submit"
                  },
                  "dataToSend" : {
                    "type" : "expression",
                    "value" : "formOutput"
                  },
                  "dataFromError" : {
                    "type" : "variable",
                    "value" : "formOutput._submitError"
                  },
                  "allowHTML" : {
                    "type" : "constant",
                    "value" : false
                  },
                  "labelHidden" : {
                    "type" : "constant",
                    "value" : false
                  },
                  "collectionPosition" : {
                    "type" : "constant"
                  },
                  "targetUrlOnSuccess" : {
                    "type" : "interpolation",
                    "value" : "/bonita"
                  },
                  "action" : {
                    "type" : "constant",
                    "value" : "Submit task"
                  },
                  "collectionToModify" : {
                    "type" : "variable"
                  },
                  "valueToAdd" : {
                    "type" : "expression"
                  },
                  "disabled" : {
                    "type" : "expression",
                    "value" : "$form.$invalid"
                  },
                  "alignment" : {
                    "type" : "constant",
                    "value" : "center"
                  },
                  "dimension" : {
                    "type" : "constant",
                    "value" : 12
                  }
                },
                "reference" : "854b63d8-f08d-4ef1-9619-61bd97adc489",
                "hasValidationError" : false,
                "id" : "pbButton",
                "description" : ""
              }
            ],
            [
              {
                "type" : "component",
                "dimension" : {
                  "md" : 12,
                  "sm" : 12,
                  "xs" : 12,
                  "lg" : 12
                },
                "propertyValues" : {
                  "allowHTML" : {
                    "type" : "constant",
                    "value" : true
                  },
                  "allowHtml" : {
                    "type" : "constant",
                    "value" : true
                  },
                  "labelHidden" : {
                    "type" : "constant",
                    "value" : true
                  },
                  "hidden" : {
                    "type" : "expression",
                    "value" : "!formOutput._submitError.message"
                  },
                  "cssClasses" : {
                    "type" : "constant",
                    "value" : "alert alert-danger col-lg-6 col-lg-offset-3"
                  },
                  "label" : {
                    "type" : "interpolation"
                  },
                  "text" : {
                    "type" : "interpolation",
                    "value" : "<strong>Debug message</strong>\n<br/>\n{{formOutput._submitError.message}}\n{{submit_errors_list}}"
                  },
                  "alignment" : {
                    "type" : "constant",
                    "value" : "left"
                  },
                  "dimension" : {
                    "type" : "constant",
                    "value" : 12
                  }
                },
                "reference" : "aad268e0-4ca5-4b66-99f7-a41fa15b44d1",
                "hasValidationError" : false,
                "id" : "pbText",
                "description" : ""
              }
            ]
          ]
        }
      }
    ]
  ],
  "variables" : {
    "task" : {
      "type" : "url",
      "value" : [
        "../API/bpm/userTask/{{taskId}}"
      ],
      "exposed" : false
    },
    "submit_errors_list" : {
      "type" : "expression",
      "value" : [
        "if($data.formOutput && $data.formOutput._submitError && $data.formOutput._submitError.explanations){",
        "\tconst liElements = $data.formOutput._submitError.explanations",
        "\t\t.filter(cause => cause !== null)",
        "\t\t.map(cause => \"<li>\" + cause + \"</li>\")",
        "\t\t.join('');",
        "\tif(liElements){",
        "\t\treturn \"<ul>\" + liElements + \"</ul>\";",
        "\t}",
        "}"
      ],
      "exposed" : false
    },
    "formOutput" : {
      "type" : "expression",
      "value" : [
        "if( $data.variableInv ){",
        "\treturn {",
        "\t\t//map variableInv variable to expected task contract input",
        "\t\tvariableInvInput: {",
        "\t\t\tobservaciones_revision: $data.variableInv.observaciones_revision !== undefined ? $data.variableInv.observaciones_revision : null",
        "\t\t}",
        "\t}",
        "}"
      ],
      "exposed" : false
    },
    "context" : {
      "type" : "url",
      "value" : [
        "../API/bpm/userTask/{{taskId}}/context"
      ],
      "exposed" : false
    },
    "taskId" : {
      "type" : "urlparameter",
      "value" : [
        "id"
      ],
      "exposed" : false
    },
    "variableInv" : {
      "type" : "url",
      "value" : [
        "../{{context.variableInv_ref.link}}"
      ],
      "exposed" : false
    }
  },
  "assets" : [
    {
      "id" : "0668e9ec-fa40-4695-a55e-2a72cee69abb",
      "name" : "style.css",
      "type" : "css",
      "order" : 0,
      "external" : false
    },
    {
      "id" : "af0c3bab-befd-4e7f-a1c7-776475f7cd02",
      "name" : "localization.json",
      "type" : "json",
      "order" : 0,
      "external" : false
    }
  ],
  "inactiveAssets" : [ ],
  "webResources" : [ ],
  "hasValidationError" : false
}